bluetarget/__init__.py
bluetarget/api_endpoint.py
bluetarget/bluetarget.py
bluetarget/bluetarget_types.py
bluetarget/constants.py
bluetarget/entities.py
bluetarget/errors.py
bluetarget/model.py
bluetarget/model_version.py
bluetarget/monitor.py
bluetarget/utils.py
bluetarget/validation.py
bluetarget-0.3.1.dist-info/WHEEL
bluetarget-0.3.1.dist-info/METADATA
bluetarget-0.3.1.dist-info/RECORD
