Metadata-Version: 2.1
Name: bluetarget
Version: 0.3.1
Summary: Deploy, monitor and explain your machine learning models
Author: Sergio Kaz
Author-email: sergio@bluetarget.ai
Requires-Python: >=3.7
Classifier: Programming Language :: Python :: 3
Classifier: Programming Language :: Python :: 3.7
Classifier: Programming Language :: Python :: 3.8
Classifier: Programming Language :: Python :: 3.9
Classifier: Programming Language :: Python :: 3.10
Classifier: Programming Language :: Python :: 3.11
Requires-Dist: click (>=8.0)
Requires-Dist: pandas (>=1.3.5)
Requires-Dist: pyarrow (>=7.0)
Requires-Dist: pydantic (>=1.9)
Requires-Dist: requests (>=2.27)
